[
  {
    "courses": [
      "MATH",
      "READING",
      "SCIENCE"
    ],
    "grade": 10,
    "name": "Genevie Stokes",
    "id": 0,
    "frequency": 3
  },
  {
    "courses": [
      "MATH",
      "WRITING",
      "SCIENCE",
      "HISTORY"
    ],
    "grade": 2,
    "name": "Soraya Kunze",
    "id": 1,
    "frequency": 5
  },
  {
    "courses": [
      "SCIENCE"
    ],
    "grade": 10,
    "name": "Vicenta Howe",
    "id": 2,
    "frequency": 2
  },
  {
    "courses": [
      "MATH",
      "READING"
    ],
    "grade": 5,
    "name": "Season Abbott",
    "id": 3,
    "frequency": 5
  },
  {
    "courses": [
      "WRITING"
    ],
    "grade": 9,
    "name": "Claretta Williamson",
    "id": 4,
    "frequency": 4
  },
  {
    "courses": [
      "READING"
    ],
    "grade": 4,
    "name": "Allan Feil",
    "id": 5,
    "frequency": 2
  },
  {
    "courses": [
      "WRITING",
      "SCIENCE"
    ],
    "grade": 8,
    "name": "Vern Ryan",
    "id": 6,
    "frequency": 6
  },
  {
    "courses": [
      "MATH",
      "READING",
      "WRITING",
      "HISTORY"
    ],
    "grade": 7,
    "name": "Nola Nicolas",
    "id": 7,
    "frequency": 3
  },
  {
    "courses": [
      "MATH",
      "SCIENCE"
    ],
    "grade": 10,
    "name": "Kevin Kshlerin",
    "id": 8,
    "frequency": 2
  },
  {
    "courses": [
      "READING",
      "SCIENCE"
    ],
    "grade": 2,
    "name": "Wilmer Nienow",
    "id": 9,
    "frequency": 2
  },
  {
    "courses": [
      "MATH",
      "HISTORY"
    ],
    "grade": 4,
    "name": "Paige Kunde",
    "id": 10,
    "frequency": 6
  },
  {
    "courses": [
      "MATH",
      "WRITING",
      "SCIENCE",
      "HISTORY"
    ],
    "grade": 7,
    "name": "Johnathon Weissnat",
    "id": 11,
    "frequency": 4
  },
  {
    "courses": [
      "WRITING",
      "SCIENCE",
      "HISTORY"
    ],
    "grade": 8,
    "name": "Ignacia Roberts",
    "id": 12,
    "frequency": 4
  },
  {
    "courses": [
      "READING",
      "WRITING"
    ],
    "grade": 7,
    "name": "Jannie Rogahn",
    "id": 13,
    "frequency": 2
  },
  {
    "courses": [],
    "grade": 8,
    "name": "Cristopher Schoen",
    "id": 14,
    "frequency": 3
  },
  {
    "courses": [
      "WRITING",
      "SCIENCE"
    ],
    "grade": 9,
    "name": "Zola Bernier",
    "id": 15,
    "frequency": 6
  },
  {
    "courses": [
      "READING",
      "WRITING"
    ],
    "grade": 2,
    "name": "Chuck Kuhn",
    "id": 16,
    "frequency": 6
  },
  {
    "courses": [
      "MATH",
      "READING"
    ],
    "grade": 8,
    "name": "Fran Adams",
    "id": 17,
    "frequency": 5
  },
  {
    "courses": [
      "MATH",
      "SCIENCE",
      "HISTORY"
    ],
    "grade": 4,
    "name": "Kathrine Ziemann",
    "id": 18,
    "frequency": 1
  },
  {
    "courses": [
      "MATH",
      "WRITING",
      "SCIENCE"
    ],
    "grade": 7,
    "name": "Dwayne Waters",
    "id": 19,
    "frequency": 4
  },
  {
    "courses": [
      "MATH",
      "READING",
      "SCIENCE"
    ],
    "grade": 10,
    "name": "Beverly Hickle",
    "id": 20,
    "frequency": 5
  },
  {
    "courses": [
      "MATH",
      "WRITING"
    ],
    "grade": 4,
    "name": "Son Bartoletti",
    "id": 21,
    "frequency": 2
  },
  {
    "courses": [
      "MATH",
      "WRITING",
      "SCIENCE",
      "HISTORY"
    ],
    "grade": 3,
    "name": "Rufina Mitchell",
    "id": 22,
    "frequency": 4
  },
  {
    "courses": [
      "HISTORY"
    ],
    "grade": 8,
    "name": "Bart Hagenes",
    "id": 23,
    "frequency": 4
  },
  {
    "courses": [
      "READING",
      "SCIENCE"
    ],
    "grade": 1,
    "name": "Quincy Beatty",
    "id": 24,
    "frequency": 1
  },
  {
    "courses": [
      "MATH",
      "HISTORY"
    ],
    "grade": 7,
    "name": "Harry VonRueden",
    "id": 25,
    "frequency": 1
  },
  {
    "courses": [
      "MATH",
      "READING",
      "SCIENCE"
    ],
    "grade": 10,
    "name": "Manuel Jenkins",
    "id": 26,
    "frequency": 6
  },
  {
    "courses": [
      "WRITING"
    ],
    "grade": 9,
    "name": "Ronnie Funk",
    "id": 27,
    "frequency": 4
  },
  {
    "courses": [
      "MATH",
      "WRITING"
    ],
    "grade": 10,
    "name": "Ryan Kling",
    "id": 28,
    "frequency": 5
  },
  {
    "courses": [
      "MATH",
      "READING",
      "SCIENCE"
    ],
    "grade": 6,
    "name": "Rosaria Rath",
    "id": 29,
    "frequency": 4
  },
  {
    "courses": [],
    "grade": 10,
    "name": "Hobert Wilderman",
    "id": 30,
    "frequency": 2
  },
  {
    "courses": [
      "HISTORY"
    ],
    "grade": 9,
    "name": "Daryl Renner",
    "id": 31,
    "frequency": 2
  },
  {
    "courses": [
      "READING",
      "WRITING",
      "SCIENCE",
      "HISTORY"
    ],
    "grade": 6,
    "name": "Warren Hartmann",
    "id": 32,
    "frequency": 3
  },
  {
    "courses": [
      "MATH",
      "WRITING",
      "HISTORY"
    ],
    "grade": 2,
    "name": "Suzy Kunze",
    "id": 33,
    "frequency": 3
  },
  {
    "courses": [
      "WRITING",
      "HISTORY"
    ],
    "grade": 5,
    "name": "Rodney Bode",
    "id": 34,
    "frequency": 6
  },
  {
    "courses": [
      "READING",
      "WRITING",
      "HISTORY"
    ],
    "grade": 10,
    "name": "Vern Cassin",
    "id": 35,
    "frequency": 3
  },
  {
    "courses": [
      "READING",
      "SCIENCE"
    ],
    "grade": 5,
    "name": "Lisette Paucek",
    "id": 36,
    "frequency": 3
  },
  {
    "courses": [
      "READING",
      "SCIENCE"
    ],
    "grade": 4,
    "name": "Brinda Bahringer",
    "id": 37,
    "frequency": 6
  },
  {
    "courses": [
      "MATH",
      "READING",
      "WRITING",
      "SCIENCE",
      "HISTORY"
    ],
    "grade": 6,
    "name": "Donald Schowalter",
    "id": 38,
    "frequency": 5
  },
  {
    "courses": [
      "MATH",
      "READING",
      "HISTORY"
    ],
    "grade": 5,
    "name": "Andres Kohler",
    "id": 39,
    "frequency": 3
  },
  {
    "courses": [
      "MATH",
      "SCIENCE",
      "HISTORY"
    ],
    "grade": 11,
    "name": "Kerri Leffler",
    "id": 40,
    "frequency": 6
  },
  {
    "courses": [
      "READING",
      "WRITING",
      "SCIENCE"
    ],
    "grade": 2,
    "name": "Jo Pfannerstill",
    "id": 41,
    "frequency": 5
  },
  {
    "courses": [
      "READING",
      "SCIENCE",
      "HISTORY"
    ],
    "grade": 5,
    "name": "Patrick Schmitt",
    "id": 42,
    "frequency": 5
  },
  {
    "courses": [
      "MATH",
      "READING"
    ],
    "grade": 9,
    "name": "Carey Brakus",
    "id": 43,
    "frequency": 5
  },
  {
    "courses": [
      "MATH",
      "READING",
      "WRITING",
      "SCIENCE",
      "HISTORY"
    ],
    "grade": 9,
    "name": "Dolly Herman",
    "id": 44,
    "frequency": 1
  },
  {
    "courses": [
      "READING",
      "SCIENCE"
    ],
    "grade": 3,
    "name": "Tai Reynolds",
    "id": 45,
    "frequency": 4
  },
  {
    "courses": [
      "MATH",
      "SCIENCE",
      "HISTORY"
    ],
    "grade": 6,
    "name": "Eden Weber",
    "id": 46,
    "frequency": 6
  },
  {
    "courses": [
      "READING",
      "WRITING",
      "HISTORY"
    ],
    "grade": 9,
    "name": "Almeda Mohr",
    "id": 47,
    "frequency": 2
  },
  {
    "courses": [
      "MATH",
      "READING",
      "WRITING",
      "HISTORY"
    ],
    "grade": 6,
    "name": "Krystina Shields",
    "id": 48,
    "frequency": 3
  },
  {
    "courses": [
      "READING",
      "WRITING",
      "SCIENCE",
      "HISTORY"
    ],
    "grade": 4,
    "name": "Sachiko Larkin",
    "id": 49,
    "frequency": 5
  },
  {
    "courses": [
      "WRITING",
      "SCIENCE",
      "HISTORY"
    ],
    "grade": 2,
    "name": "Obdulia Von",
    "id": 50,
    "frequency": 5
  },
  {
    "courses": [
      "MATH",
      "WRITING",
      "SCIENCE"
    ],
    "grade": 8,
    "name": "Daryl Stiedemann",
    "id": 51,
    "frequency": 4
  },
  {
    "courses": [
      "MATH",
      "WRITING",
      "SCIENCE"
    ],
    "grade": 1,
    "name": "Shara Toy",
    "id": 52,
    "frequency": 4
  },
  {
    "courses": [
      "WRITING",
      "SCIENCE"
    ],
    "grade": 4,
    "name": "Almeta Stracke",
    "id": 53,
    "frequency": 5
  },
  {
    "courses": [
      "READING",
      "HISTORY"
    ],
    "grade": 7,
    "name": "Jadwiga Hartmann",
    "id": 54,
    "frequency": 3
  },
  {
    "courses": [
      "MATH",
      "WRITING"
    ],
    "grade": 6,
    "name": "Jeremy Bogan",
    "id": 55,
    "frequency": 1
  },
  {
    "courses": [
      "READING",
      "WRITING",
      "SCIENCE"
    ],
    "grade": 5,
    "name": "Sidney Gislason",
    "id": 56,
    "frequency": 2
  },
  {
    "courses": [
      "SCIENCE",
      "HISTORY"
    ],
    "grade": 7,
    "name": "Love Goodwin",
    "id": 57,
    "frequency": 3
  },
  {
    "courses": [
      "MATH",
      "WRITING"
    ],
    "grade": 2,
    "name": "Fred Kutch",
    "id": 58,
    "frequency": 2
  },
  {
    "courses": [
      "MATH",
      "READING",
      "HISTORY"
    ],
    "grade": 8,
    "name": "Mireya Jakubowski",
    "id": 59,
    "frequency": 4
  },
  {
    "courses": [
      "READING",
      "WRITING"
    ],
    "grade": 10,
    "name": "Chang Rath",
    "id": 60,
    "frequency": 4
  },
  {
    "courses": [],
    "grade": 10,
    "name": "Robbi Auer",
    "id": 61,
    "frequency": 1
  },
  {
    "courses": [
      "READING",
      "WRITING",
      "SCIENCE"
    ],
    "grade": 3,
    "name": "Erich Ankunding",
    "id": 62,
    "frequency": 3
  },
  {
    "courses": [
      "READING",
      "WRITING",
      "SCIENCE",
      "HISTORY"
    ],
    "grade": 5,
    "name": "Ike Wyman",
    "id": 63,
    "frequency": 5
  },
  {
    "courses": [
      "MATH",
      "READING",
      "WRITING",
      "SCIENCE"
    ],
    "grade": 1,
    "name": "Margie Huel",
    "id": 64,
    "frequency": 4
  },
  {
    "courses": [
      "SCIENCE",
      "HISTORY"
    ],
    "grade": 9,
    "name": "Zenia Tromp",
    "id": 65,
    "frequency": 5
  },
  {
    "courses": [
      "MATH",
      "WRITING"
    ],
    "grade": 11,
    "name": "Catina Daniel",
    "id": 66,
    "frequency": 5
  },
  {
    "courses": [
      "READING",
      "HISTORY"
    ],
    "grade": 1,
    "name": "Augustus Howe",
    "id": 67,
    "frequency": 3
  },
  {
    "courses": [
      "MATH",
      "READING",
      "SCIENCE"
    ],
    "grade": 11,
    "name": "Stephine Ward",
    "id": 68,
    "frequency": 4
  },
  {
    "courses": [
      "WRITING",
      "SCIENCE",
      "HISTORY"
    ],
    "grade": 5,
    "name": "Robin Haley",
    "id": 69,
    "frequency": 2
  },
  {
    "courses": [
      "MATH",
      "SCIENCE",
      "HISTORY"
    ],
    "grade": 1,
    "name": "Johanna Carroll",
    "id": 70,
    "frequency": 1
  },
  {
    "courses": [
      "WRITING",
      "HISTORY"
    ],
    "grade": 2,
    "name": "Ching Russel",
    "id": 71,
    "frequency": 5
  },
  {
    "courses": [
      "WRITING",
      "SCIENCE",
      "HISTORY"
    ],
    "grade": 5,
    "name": "Noelia Herzog",
    "id": 72,
    "frequency": 2
  },
  {
    "courses": [],
    "grade": 11,
    "name": "Dewayne Bartoletti",
    "id": 73,
    "frequency": 2
  },
  {
    "courses": [],
    "grade": 5,
    "name": "Casimira Frami",
    "id": 74,
    "frequency": 3
  },
  {
    "courses": [
      "SCIENCE",
      "HISTORY"
    ],
    "grade": 11,
    "name": "Patricia Yost",
    "id": 75,
    "frequency": 6
  },
  {
    "courses": [
      "HISTORY"
    ],
    "grade": 9,
    "name": "Rosalie Stanton",
    "id": 76,
    "frequency": 5
  },
  {
    "courses": [
      "MATH",
      "HISTORY"
    ],
    "grade": 5,
    "name": "Stefany Dickens",
    "id": 77,
    "frequency": 5
  },
  {
    "courses": [
      "MATH",
      "HISTORY"
    ],
    "grade": 10,
    "name": "Bernadine Murray",
    "id": 78,
    "frequency": 3
  },
  {
    "courses": [
      "MATH",
      "READING",
      "WRITING",
      "SCIENCE"
    ],
    "grade": 6,
    "name": "Bertram Turcotte",
    "id": 79,
    "frequency": 6
  },
  {
    "courses": [
      "READING",
      "SCIENCE"
    ],
    "grade": 2,
    "name": "Peggie Nolan",
    "id": 80,
    "frequency": 2
  },
  {
    "courses": [
      "WRITING",
      "SCIENCE",
      "HISTORY"
    ],
    "grade": 6,
    "name": "Lu Treutel",
    "id": 81,
    "frequency": 6
  },
  {
    "courses": [
      "HISTORY"
    ],
    "grade": 10,
    "name": "Florene Konopelski",
    "id": 82,
    "frequency": 1
  },
  {
    "courses": [
      "MATH",
      "READING",
      "SCIENCE",
      "HISTORY"
    ],
    "grade": 10,
    "name": "Tiesha Crooks",
    "id": 83,
    "frequency": 3
  },
  {
    "courses": [
      "READING",
      "WRITING",
      "SCIENCE"
    ],
    "grade": 5,
    "name": "Malcolm Leffler",
    "id": 84,
    "frequency": 4
  },
  {
    "courses": [
      "MATH",
      "READING",
      "SCIENCE",
      "HISTORY"
    ],
    "grade": 9,
    "name": "Eldon Hintz",
    "id": 85,
    "frequency": 3
  },
  {
    "courses": [
      "MATH",
      "READING",
      "WRITING",
      "SCIENCE",
      "HISTORY"
    ],
    "grade": 8,
    "name": "Monty Donnelly",
    "id": 86,
    "frequency": 3
  },
  {
    "courses": [
      "SCIENCE",
      "HISTORY"
    ],
    "grade": 10,
    "name": "Babara Wilkinson",
    "id": 87,
    "frequency": 4
  },
  {
    "courses": [
      "READING",
      "HISTORY"
    ],
    "grade": 10,
    "name": "Paulene Farrell",
    "id": 88,
    "frequency": 4
  },
  {
    "courses": [
      "HISTORY"
    ],
    "grade": 8,
    "name": "Cole Lebsack",
    "id": 89,
    "frequency": 4
  },
  {
    "courses": [
      "MATH",
      "READING",
      "HISTORY"
    ],
    "grade": 4,
    "name": "Shelia Volkman",
    "id": 90,
    "frequency": 2
  },
  {
    "courses": [
      "MATH",
      "READING",
      "HISTORY"
    ],
    "grade": 3,
    "name": "Carman Lubowitz",
    "id": 91,
    "frequency": 5
  },
  {
    "courses": [
      "MATH",
      "READING",
      "WRITING",
      "SCIENCE"
    ],
    "grade": 10,
    "name": "Vance Kirlin",
    "id": 92,
    "frequency": 5
  },
  {
    "courses": [
      "READING",
      "SCIENCE",
      "HISTORY"
    ],
    "grade": 9,
    "name": "Dede Kautzer",
    "id": 93,
    "frequency": 6
  },
  {
    "courses": [
      "HISTORY"
    ],
    "grade": 3,
    "name": "Nicki Balistreri",
    "id": 94,
    "frequency": 1
  },
  {
    "courses": [
      "MATH",
      "WRITING",
      "SCIENCE",
      "HISTORY"
    ],
    "grade": 9,
    "name": "Crystal Lehner",
    "id": 95,
    "frequency": 5
  },
  {
    "courses": [
      "MATH",
      "SCIENCE"
    ],
    "grade": 1,
    "name": "Garrett Denesik",
    "id": 96,
    "frequency": 6
  },
  {
    "courses": [
      "MATH"
    ],
    "grade": 2,
    "name": "Herschel Miller",
    "id": 97,
    "frequency": 5
  },
  {
    "courses": [
      "WRITING",
      "SCIENCE",
      "HISTORY"
    ],
    "grade": 5,
    "name": "Dianna Cassin",
    "id": 98,
    "frequency": 1
  },
  {
    "courses": [
      "MATH"
    ],
    "grade": 2,
    "name": "Nadia Emmerich",
    "id": 99,
    "frequency": 4
  },
  {
    "courses": [
      "WRITING"
    ],
    "grade": 10,
    "name": "Inell Cummerata",
    "id": 100,
    "frequency": 3
  },
  {
    "courses": [
      "MATH",
      "READING",
      "WRITING"
    ],
    "grade": 3,
    "name": "Cole Kunze",
    "id": 101,
    "frequency": 4
  },
  {
    "courses": [
      "READING",
      "WRITING",
      "SCIENCE",
      "HISTORY"
    ],
    "grade": 2,
    "name": "Myron Ward",
    "id": 102,
    "frequency": 3
  },
  {
    "courses": [
      "SCIENCE",
      "HISTORY"
    ],
    "grade": 2,
    "name": "Freda Blick",
    "id": 103,
    "frequency": 4
  },
  {
    "courses": [
      "MATH",
      "READING",
      "WRITING"
    ],
    "grade": 11,
    "name": "Merrill Emard",
    "id": 104,
    "frequency": 3
  },
  {
    "courses": [
      "MATH",
      "SCIENCE",
      "HISTORY"
    ],
    "grade": 11,
    "name": "Elvina Beer",
    "id": 105,
    "frequency": 2
  },
  {
    "courses": [
      "READING",
      "WRITING",
      "HISTORY"
    ],
    "grade": 4,
    "name": "Nenita Schuppe",
    "id": 106,
    "frequency": 4
  },
  {
    "courses": [
      "MATH",
      "READING",
      "WRITING"
    ],
    "grade": 5,
    "name": "Edgardo Kuhlman",
    "id": 107,
    "frequency": 6
  },
  {
    "courses": [
      "MATH",
      "READING",
      "SCIENCE"
    ],
    "grade": 11,
    "name": "Ruthie Senger",
    "id": 108,
    "frequency": 2
  },
  {
    "courses": [
      "MATH",
      "READING"
    ],
    "grade": 9,
    "name": "Merlyn Walsh",
    "id": 109,
    "frequency": 3
  },
  {
    "courses": [
      "WRITING",
      "SCIENCE",
      "HISTORY"
    ],
    "grade": 1,
    "name": "Micha Friesen",
    "id": 110,
    "frequency": 5
  },
  {
    "courses": [
      "READING",
      "SCIENCE",
      "HISTORY"
    ],
    "grade": 9,
    "name": "Ronny Schneider",
    "id": 111,
    "frequency": 3
  },
  {
    "courses": [
      "READING",
      "SCIENCE",
      "HISTORY"
    ],
    "grade": 11,
    "name": "Aldo Fisher",
    "id": 112,
    "frequency": 6
  },
  {
    "courses": [
      "MATH",
      "WRITING"
    ],
    "grade": 4,
    "name": "Mac Koelpin",
    "id": 113,
    "frequency": 4
  },
  {
    "courses": [
      "MATH",
      "READING",
      "WRITING"
    ],
    "grade": 9,
    "name": "Bradly Lind",
    "id": 114,
    "frequency": 6
  },
  {
    "courses": [
      "MATH",
      "READING",
      "WRITING",
      "SCIENCE",
      "HISTORY"
    ],
    "grade": 4,
    "name": "Lin Reichert",
    "id": 115,
    "frequency": 1
  },
  {
    "courses": [
      "WRITING",
      "SCIENCE",
      "HISTORY"
    ],
    "grade": 2,
    "name": "Giuseppe Kreiger",
    "id": 116,
    "frequency": 1
  },
  {
    "courses": [
      "READING",
      "WRITING",
      "SCIENCE",
      "HISTORY"
    ],
    "grade": 4,
    "name": "Marinda Hoppe",
    "id": 117,
    "frequency": 1
  },
  {
    "courses": [
      "READING",
      "HISTORY"
    ],
    "grade": 3,
    "name": "Stuart Thiel",
    "id": 118,
    "frequency": 4
  },
  {
    "courses": [
      "MATH",
      "READING",
      "SCIENCE"
    ],
    "grade": 9,
    "name": "Irving Orn",
    "id": 119,
    "frequency": 3
  },
  {
    "courses": [
      "MATH",
      "HISTORY"
    ],
    "grade": 7,
    "name": "Everette Mills",
    "id": 120,
    "frequency": 3
  },
  {
    "courses": [
      "MATH",
      "READING",
      "WRITING"
    ],
    "grade": 5,
    "name": "Leana Parker",
    "id": 121,
    "frequency": 3
  },
  {
    "courses": [
      "MATH",
      "READING",
      "WRITING",
      "HISTORY"
    ],
    "grade": 11,
    "name": "Erwin Kozey",
    "id": 122,
    "frequency": 5
  },
  {
    "courses": [
      "WRITING"
    ],
    "grade": 8,
    "name": "Chas Corwin",
    "id": 123,
    "frequency": 2
  },
  {
    "courses": [
      "MATH",
      "READING",
      "SCIENCE"
    ],
    "grade": 11,
    "name": "Bernie Boyer",
    "id": 124,
    "frequency": 4
  },
  {
    "courses": [
      "MATH"
    ],
    "grade": 1,
    "name": "Britany Hoeger",
    "id": 125,
    "frequency": 3
  },
  {
    "courses": [
      "MATH",
      "READING",
      "WRITING",
      "SCIENCE"
    ],
    "grade": 5,
    "name": "Thersa Wiza",
    "id": 126,
    "frequency": 6
  },
  {
    "courses": [
      "READING",
      "WRITING",
      "HISTORY"
    ],
    "grade": 10,
    "name": "Boyd Stiedemann",
    "id": 127,
    "frequency": 3
  },
  {
    "courses": [
      "READING"
    ],
    "grade": 3,
    "name": "Ellis Stracke",
    "id": 128,
    "frequency": 5
  },
  {
    "courses": [
      "MATH",
      "WRITING",
      "SCIENCE",
      "HISTORY"
    ],
    "grade": 10,
    "name": "Irving Hirthe",
    "id": 129,
    "frequency": 5
  },
  {
    "courses": [
      "MATH",
      "WRITING",
      "SCIENCE"
    ],
    "grade": 1,
    "name": "Lillie Zboncak",
    "id": 130,
    "frequency": 2
  },
  {
    "courses": [
      "READING",
      "WRITING",
      "HISTORY"
    ],
    "grade": 2,
    "name": "Sylvie Koss",
    "id": 131,
    "frequency": 6
  },
  {
    "courses": [
      "MATH",
      "WRITING",
      "SCIENCE"
    ],
    "grade": 8,
    "name": "Alvaro Jerde",
    "id": 132,
    "frequency": 4
  },
  {
    "courses": [
      "WRITING",
      "SCIENCE"
    ],
    "grade": 1,
    "name": "Darnell Hoppe",
    "id": 133,
    "frequency": 5
  },
  {
    "courses": [
      "READING",
      "SCIENCE",
      "HISTORY"
    ],
    "grade": 7,
    "name": "Debora Hoeger",
    "id": 134,
    "frequency": 6
  },
  {
    "courses": [
      "MATH",
      "READING",
      "WRITING",
      "HISTORY"
    ],
    "grade": 7,
    "name": "Hollie Parisian",
    "id": 135,
    "frequency": 3
  },
  {
    "courses": [
      "MATH",
      "READING"
    ],
    "grade": 1,
    "name": "Marianna Olson",
    "id": 136,
    "frequency": 3
  },
  {
    "courses": [
      "READING",
      "WRITING",
      "SCIENCE"
    ],
    "grade": 6,
    "name": "Ted Roob",
    "id": 137,
    "frequency": 6
  },
  {
    "courses": [
      "SCIENCE",
      "HISTORY"
    ],
    "grade": 8,
    "name": "Aleshia Wolf",
    "id": 138,
    "frequency": 6
  },
  {
    "courses": [
      "READING"
    ],
    "grade": 1,
    "name": "Maurice Hoppe",
    "id": 139,
    "frequency": 3
  },
  {
    "courses": [
      "MATH",
      "WRITING"
    ],
    "grade": 9,
    "name": "Elias Gislason",
    "id": 140,
    "frequency": 2
  },
  {
    "courses": [
      "WRITING"
    ],
    "grade": 5,
    "name": "Corie O\u0027Connell",
    "id": 141,
    "frequency": 3
  },
  {
    "courses": [
      "READING",
      "WRITING"
    ],
    "grade": 10,
    "name": "Stacy Turcotte",
    "id": 142,
    "frequency": 5
  },
  {
    "courses": [
      "MATH",
      "READING",
      "WRITING",
      "SCIENCE"
    ],
    "grade": 5,
    "name": "Kurtis Huel",
    "id": 143,
    "frequency": 6
  },
  {
    "courses": [
      "READING",
      "SCIENCE"
    ],
    "grade": 4,
    "name": "Prince McCullough",
    "id": 144,
    "frequency": 4
  },
  {
    "courses": [
      "MATH",
      "WRITING"
    ],
    "grade": 7,
    "name": "Sherwood Wilderman",
    "id": 145,
    "frequency": 3
  },
  {
    "courses": [
      "MATH",
      "SCIENCE",
      "HISTORY"
    ],
    "grade": 6,
    "name": "Gertie Stokes",
    "id": 146,
    "frequency": 4
  },
  {
    "courses": [
      "MATH",
      "SCIENCE"
    ],
    "grade": 5,
    "name": "Dong Kuhn",
    "id": 147,
    "frequency": 4
  },
  {
    "courses": [
      "SCIENCE"
    ],
    "grade": 6,
    "name": "Nestor Jones",
    "id": 148,
    "frequency": 5
  },
  {
    "courses": [
      "WRITING",
      "SCIENCE"
    ],
    "grade": 2,
    "name": "Jazmine Haley",
    "id": 149,
    "frequency": 3
  },
  {
    "courses": [
      "WRITING",
      "SCIENCE",
      "HISTORY"
    ],
    "grade": 5,
    "name": "Verline Kihn",
    "id": 150,
    "frequency": 3
  },
  {
    "courses": [
      "MATH",
      "READING",
      "WRITING"
    ],
    "grade": 9,
    "name": "Chad Gerlach",
    "id": 151,
    "frequency": 4
  },
  {
    "courses": [
      "READING"
    ],
    "grade": 1,
    "name": "Henry Hane",
    "id": 152,
    "frequency": 4
  },
  {
    "courses": [
      "MATH",
      "SCIENCE",
      "HISTORY"
    ],
    "grade": 8,
    "name": "Jed Hills",
    "id": 153,
    "frequency": 1
  },
  {
    "courses": [
      "MATH",
      "READING",
      "WRITING",
      "HISTORY"
    ],
    "grade": 3,
    "name": "Leif Swaniawski",
    "id": 154,
    "frequency": 3
  },
  {
    "courses": [
      "MATH",
      "READING"
    ],
    "grade": 5,
    "name": "Russ Mitchell",
    "id": 155,
    "frequency": 2
  },
  {
    "courses": [
      "MATH",
      "SCIENCE",
      "HISTORY"
    ],
    "grade": 4,
    "name": "Cristi Gutkowski",
    "id": 156,
    "frequency": 4
  },
  {
    "courses": [
      "WRITING"
    ],
    "grade": 3,
    "name": "Efrain Schoen",
    "id": 157,
    "frequency": 4
  },
  {
    "courses": [
      "MATH",
      "WRITING"
    ],
    "grade": 3,
    "name": "Blanch Kuphal",
    "id": 158,
    "frequency": 4
  },
  {
    "courses": [
      "MATH",
      "READING",
      "WRITING",
      "SCIENCE",
      "HISTORY"
    ],
    "grade": 11,
    "name": "Luann Mante",
    "id": 159,
    "frequency": 2
  },
  {
    "courses": [
      "MATH",
      "READING",
      "SCIENCE"
    ],
    "grade": 10,
    "name": "Bonny Torp",
    "id": 160,
    "frequency": 3
  },
  {
    "courses": [
      "SCIENCE"
    ],
    "grade": 3,
    "name": "Alfreda Spinka",
    "id": 161,
    "frequency": 4
  },
  {
    "courses": [
      "WRITING",
      "SCIENCE",
      "HISTORY"
    ],
    "grade": 1,
    "name": "Rheba Mueller",
    "id": 162,
    "frequency": 5
  },
  {
    "courses": [
      "READING",
      "WRITING"
    ],
    "grade": 3,
    "name": "Lucien West",
    "id": 163,
    "frequency": 3
  },
  {
    "courses": [
      "MATH",
      "SCIENCE"
    ],
    "grade": 7,
    "name": "Lloyd Kemmer",
    "id": 164,
    "frequency": 5
  },
  {
    "courses": [
      "MATH",
      "WRITING",
      "SCIENCE"
    ],
    "grade": 3,
    "name": "Grady Olson",
    "id": 165,
    "frequency": 3
  },
  {
    "courses": [
      "MATH",
      "SCIENCE",
      "HISTORY"
    ],
    "grade": 4,
    "name": "Harris Stokes",
    "id": 166,
    "frequency": 2
  },
  {
    "courses": [
      "READING",
      "HISTORY"
    ],
    "grade": 9,
    "name": "Enoch Weimann",
    "id": 167,
    "frequency": 2
  },
  {
    "courses": [
      "MATH",
      "WRITING",
      "SCIENCE",
      "HISTORY"
    ],
    "grade": 4,
    "name": "Delbert Adams",
    "id": 168,
    "frequency": 3
  },
  {
    "courses": [
      "MATH",
      "READING",
      "WRITING",
      "HISTORY"
    ],
    "grade": 2,
    "name": "Newton Hammes",
    "id": 169,
    "frequency": 1
  },
  {
    "courses": [
      "MATH",
      "WRITING",
      "SCIENCE",
      "HISTORY"
    ],
    "grade": 6,
    "name": "Hipolito Walsh",
    "id": 170,
    "frequency": 1
  },
  {
    "courses": [
      "MATH",
      "READING",
      "WRITING",
      "SCIENCE",
      "HISTORY"
    ],
    "grade": 8,
    "name": "Sueann Stehr",
    "id": 171,
    "frequency": 2
  },
  {
    "courses": [
      "MATH",
      "SCIENCE",
      "HISTORY"
    ],
    "grade": 3,
    "name": "Moshe Abernathy",
    "id": 172,
    "frequency": 1
  },
  {
    "courses": [
      "WRITING",
      "SCIENCE"
    ],
    "grade": 4,
    "name": "Austin Kohler",
    "id": 173,
    "frequency": 2
  },
  {
    "courses": [
      "READING",
      "WRITING",
      "SCIENCE"
    ],
    "grade": 4,
    "name": "Frederic Goodwin",
    "id": 174,
    "frequency": 1
  },
  {
    "courses": [
      "MATH",
      "WRITING",
      "SCIENCE",
      "HISTORY"
    ],
    "grade": 8,
    "name": "Monte Frami",
    "id": 175,
    "frequency": 2
  },
  {
    "courses": [
      "WRITING",
      "HISTORY"
    ],
    "grade": 8,
    "name": "Ezekiel Davis",
    "id": 176,
    "frequency": 5
  },
  {
    "courses": [
      "READING",
      "WRITING",
      "SCIENCE",
      "HISTORY"
    ],
    "grade": 6,
    "name": "Clarissa Keebler",
    "id": 177,
    "frequency": 2
  },
  {
    "courses": [
      "READING",
      "HISTORY"
    ],
    "grade": 4,
    "name": "Buster Huel",
    "id": 178,
    "frequency": 4
  },
  {
    "courses": [
      "MATH",
      "READING",
      "WRITING",
      "SCIENCE",
      "HISTORY"
    ],
    "grade": 7,
    "name": "Federico Feeney",
    "id": 179,
    "frequency": 4
  },
  {
    "courses": [
      "READING"
    ],
    "grade": 5,
    "name": "Stanford Mueller",
    "id": 180,
    "frequency": 5
  },
  {
    "courses": [
      "MATH",
      "READING",
      "WRITING"
    ],
    "grade": 5,
    "name": "Drucilla Howe",
    "id": 181,
    "frequency": 6
  },
  {
    "courses": [
      "MATH",
      "HISTORY"
    ],
    "grade": 9,
    "name": "Michelle Homenick",
    "id": 182,
    "frequency": 6
  },
  {
    "courses": [
      "READING",
      "HISTORY"
    ],
    "grade": 11,
    "name": "Jimmy Gutkowski",
    "id": 183,
    "frequency": 3
  },
  {
    "courses": [
      "MATH",
      "WRITING",
      "SCIENCE",
      "HISTORY"
    ],
    "grade": 7,
    "name": "Garland Stark",
    "id": 184,
    "frequency": 5
  },
  {
    "courses": [
      "READING",
      "SCIENCE"
    ],
    "grade": 1,
    "name": "Austin Schultz",
    "id": 185,
    "frequency": 5
  },
  {
    "courses": [
      "MATH",
      "READING",
      "WRITING",
      "HISTORY"
    ],
    "grade": 3,
    "name": "Lenny Cummerata",
    "id": 186,
    "frequency": 4
  },
  {
    "courses": [
      "READING",
      "HISTORY"
    ],
    "grade": 9,
    "name": "Randal Zemlak",
    "id": 187,
    "frequency": 2
  },
  {
    "courses": [
      "MATH",
      "WRITING",
      "HISTORY"
    ],
    "grade": 11,
    "name": "Marlene Rohan",
    "id": 188,
    "frequency": 2
  },
  {
    "courses": [
      "MATH",
      "READING",
      "WRITING",
      "SCIENCE",
      "HISTORY"
    ],
    "grade": 4,
    "name": "Lincoln Parisian",
    "id": 189,
    "frequency": 4
  },
  {
    "courses": [
      "READING",
      "SCIENCE"
    ],
    "grade": 7,
    "name": "Narcisa Lehner",
    "id": 190,
    "frequency": 3
  },
  {
    "courses": [
      "MATH",
      "WRITING",
      "HISTORY"
    ],
    "grade": 5,
    "name": "Julio Larson",
    "id": 191,
    "frequency": 5
  },
  {
    "courses": [
      "MATH",
      "WRITING",
      "HISTORY"
    ],
    "grade": 8,
    "name": "Gino Graham",
    "id": 192,
    "frequency": 4
  },
  {
    "courses": [
      "MATH",
      "READING",
      "SCIENCE",
      "HISTORY"
    ],
    "grade": 7,
    "name": "Pete Durgan",
    "id": 193,
    "frequency": 4
  },
  {
    "courses": [],
    "grade": 8,
    "name": "Jefferey Wyman",
    "id": 194,
    "frequency": 1
  },
  {
    "courses": [
      "MATH",
      "READING",
      "WRITING",
      "SCIENCE"
    ],
    "grade": 7,
    "name": "Stephine Kovacek",
    "id": 195,
    "frequency": 4
  },
  {
    "courses": [
      "READING",
      "WRITING"
    ],
    "grade": 10,
    "name": "Sabina Veum",
    "id": 196,
    "frequency": 4
  },
  {
    "courses": [
      "WRITING",
      "HISTORY"
    ],
    "grade": 9,
    "name": "Shandi Wiza",
    "id": 197,
    "frequency": 1
  },
  {
    "courses": [
      "MATH",
      "WRITING",
      "HISTORY"
    ],
    "grade": 2,
    "name": "Jewell Heidenreich",
    "id": 198,
    "frequency": 4
  },
  {
    "courses": [
      "MATH",
      "SCIENCE"
    ],
    "grade": 9,
    "name": "Lasonya Ward",
    "id": 199,
    "frequency": 4
  },
  {
    "courses": [
      "READING",
      "WRITING",
      "HISTORY"
    ],
    "grade": 7,
    "name": "Ezra Schulist",
    "id": 200,
    "frequency": 6
  },
  {
    "courses": [
      "READING",
      "WRITING",
      "SCIENCE",
      "HISTORY"
    ],
    "grade": 9,
    "name": "Sanford Dooley",
    "id": 201,
    "frequency": 3
  },
  {
    "courses": [
      "MATH",
      "READING",
      "SCIENCE"
    ],
    "grade": 6,
    "name": "Terrell Spinka",
    "id": 202,
    "frequency": 3
  },
  {
    "courses": [
      "MATH",
      "READING",
      "WRITING",
      "SCIENCE",
      "HISTORY"
    ],
    "grade": 4,
    "name": "Diego Quigley",
    "id": 203,
    "frequency": 3
  },
  {
    "courses": [
      "MATH",
      "READING",
      "SCIENCE",
      "HISTORY"
    ],
    "grade": 3,
    "name": "Lynn Osinski",
    "id": 204,
    "frequency": 5
  },
  {
    "courses": [
      "MATH",
      "READING",
      "WRITING",
      "HISTORY"
    ],
    "grade": 2,
    "name": "Carmelina Bashirian",
    "id": 205,
    "frequency": 5
  },
  {
    "courses": [
      "READING"
    ],
    "grade": 9,
    "name": "Vickey Davis",
    "id": 206,
    "frequency": 3
  },
  {
    "courses": [
      "MATH",
      "SCIENCE"
    ],
    "grade": 9,
    "name": "Josef McClure",
    "id": 207,
    "frequency": 4
  },
  {
    "courses": [
      "READING",
      "HISTORY"
    ],
    "grade": 2,
    "name": "Verda Yundt",
    "id": 208,
    "frequency": 2
  },
  {
    "courses": [
      "WRITING",
      "HISTORY"
    ],
    "grade": 8,
    "name": "Juan Ankunding",
    "id": 209,
    "frequency": 5
  },
  {
    "courses": [
      "READING",
      "SCIENCE",
      "HISTORY"
    ],
    "grade": 9,
    "name": "Lily Rogahn",
    "id": 210,
    "frequency": 2
  },
  {
    "courses": [
      "READING",
      "SCIENCE",
      "HISTORY"
    ],
    "grade": 8,
    "name": "Bret Schinner",
    "id": 211,
    "frequency": 4
  },
  {
    "courses": [
      "READING",
      "SCIENCE"
    ],
    "grade": 4,
    "name": "Genie Ferry",
    "id": 212,
    "frequency": 5
  },
  {
    "courses": [
      "MATH",
      "READING",
      "WRITING",
      "SCIENCE"
    ],
    "grade": 2,
    "name": "Daniel Bartell",
    "id": 213,
    "frequency": 3
  },
  {
    "courses": [
      "READING",
      "WRITING",
      "SCIENCE",
      "HISTORY"
    ],
    "grade": 4,
    "name": "Michael Hackett",
    "id": 214,
    "frequency": 1
  },
  {
    "courses": [
      "MATH",
      "WRITING"
    ],
    "grade": 5,
    "name": "Jewel Jacobson",
    "id": 215,
    "frequency": 5
  },
  {
    "courses": [
      "MATH"
    ],
    "grade": 5,
    "name": "Seth Schowalter",
    "id": 216,
    "frequency": 5
  },
  {
    "courses": [
      "MATH",
      "SCIENCE"
    ],
    "grade": 10,
    "name": "Ela Effertz",
    "id": 217,
    "frequency": 2
  },
  {
    "courses": [
      "MATH"
    ],
    "grade": 6,
    "name": "Vanita Champlin",
    "id": 218,
    "frequency": 2
  },
  {
    "courses": [
      "MATH",
      "SCIENCE"
    ],
    "grade": 7,
    "name": "Shandra Hermann",
    "id": 219,
    "frequency": 6
  },
  {
    "courses": [
      "MATH",
      "READING"
    ],
    "grade": 3,
    "name": "Taryn Dietrich",
    "id": 220,
    "frequency": 3
  },
  {
    "courses": [
      "WRITING",
      "SCIENCE"
    ],
    "grade": 10,
    "name": "Jessie Pfannerstill",
    "id": 221,
    "frequency": 3
  },
  {
    "courses": [
      "WRITING",
      "HISTORY"
    ],
    "grade": 3,
    "name": "Blake Friesen",
    "id": 222,
    "frequency": 4
  },
  {
    "courses": [
      "READING",
      "WRITING",
      "HISTORY"
    ],
    "grade": 1,
    "name": "Frankie Schiller",
    "id": 223,
    "frequency": 5
  },
  {
    "courses": [
      "READING",
      "WRITING",
      "SCIENCE",
      "HISTORY"
    ],
    "grade": 2,
    "name": "Alonso Moen",
    "id": 224,
    "frequency": 4
  },
  {
    "courses": [
      "MATH",
      "READING",
      "SCIENCE"
    ],
    "grade": 2,
    "name": "Bruce Dare",
    "id": 225,
    "frequency": 3
  },
  {
    "courses": [
      "MATH",
      "SCIENCE"
    ],
    "grade": 7,
    "name": "Sarai Kuvalis",
    "id": 226,
    "frequency": 2
  },
  {
    "courses": [
      "READING",
      "WRITING"
    ],
    "grade": 9,
    "name": "Aracelis Rosenbaum",
    "id": 227,
    "frequency": 6
  },
  {
    "courses": [
      "MATH",
      "READING"
    ],
    "grade": 4,
    "name": "Maire Murphy",
    "id": 228,
    "frequency": 5
  },
  {
    "courses": [
      "READING",
      "WRITING",
      "SCIENCE",
      "HISTORY"
    ],
    "grade": 2,
    "name": "Robby Mann",
    "id": 229,
    "frequency": 3
  },
  {
    "courses": [
      "READING",
      "WRITING",
      "SCIENCE",
      "HISTORY"
    ],
    "grade": 3,
    "name": "Edwin Beahan",
    "id": 230,
    "frequency": 2
  },
  {
    "courses": [
      "MATH",
      "SCIENCE",
      "HISTORY"
    ],
    "grade": 6,
    "name": "Charlsie Breitenberg",
    "id": 231,
    "frequency": 6
  },
  {
    "courses": [
      "SCIENCE"
    ],
    "grade": 3,
    "name": "Charisse Crist",
    "id": 232,
    "frequency": 2
  },
  {
    "courses": [
      "MATH",
      "READING",
      "WRITING",
      "HISTORY"
    ],
    "grade": 3,
    "name": "Wilfred Streich",
    "id": 233,
    "frequency": 4
  },
  {
    "courses": [
      "MATH",
      "READING",
      "SCIENCE"
    ],
    "grade": 7,
    "name": "Waldo Romaguera",
    "id": 234,
    "frequency": 4
  },
  {
    "courses": [
      "MATH"
    ],
    "grade": 8,
    "name": "Wyatt Morissette",
    "id": 235,
    "frequency": 4
  },
  {
    "courses": [
      "SCIENCE",
      "HISTORY"
    ],
    "grade": 3,
    "name": "Ward Jacobi",
    "id": 236,
    "frequency": 3
  },
  {
    "courses": [
      "MATH",
      "READING",
      "WRITING",
      "HISTORY"
    ],
    "grade": 4,
    "name": "Travis McCullough",
    "id": 237,
    "frequency": 6
  },
  {
    "courses": [
      "SCIENCE",
      "HISTORY"
    ],
    "grade": 7,
    "name": "Cordie Schamberger",
    "id": 238,
    "frequency": 2
  },
  {
    "courses": [
      "READING",
      "HISTORY"
    ],
    "grade": 3,
    "name": "Carol Parisian",
    "id": 239,
    "frequency": 4
  },
  {
    "courses": [
      "WRITING",
      "SCIENCE"
    ],
    "grade": 7,
    "name": "Coleman Kub",
    "id": 240,
    "frequency": 5
  },
  {
    "courses": [
      "MATH",
      "READING"
    ],
    "grade": 6,
    "name": "Karey Thompson",
    "id": 241,
    "frequency": 1
  },
  {
    "courses": [
      "MATH",
      "SCIENCE"
    ],
    "grade": 9,
    "name": "Jarrod Gerhold",
    "id": 242,
    "frequency": 5
  },
  {
    "courses": [
      "READING",
      "WRITING",
      "SCIENCE",
      "HISTORY"
    ],
    "grade": 6,
    "name": "Stuart Lesch",
    "id": 243,
    "frequency": 4
  },
  {
    "courses": [
      "MATH",
      "READING",
      "HISTORY"
    ],
    "grade": 1,
    "name": "Adeline Kunze",
    "id": 244,
    "frequency": 1
  },
  {
    "courses": [
      "WRITING",
      "HISTORY"
    ],
    "grade": 6,
    "name": "Kristin Thompson",
    "id": 245,
    "frequency": 4
  },
  {
    "courses": [
      "MATH",
      "WRITING",
      "HISTORY"
    ],
    "grade": 1,
    "name": "So Rolfson",
    "id": 246,
    "frequency": 5
  },
  {
    "courses": [
      "MATH",
      "READING",
      "HISTORY"
    ],
    "grade": 8,
    "name": "Walter Huels",
    "id": 247,
    "frequency": 2
  },
  {
    "courses": [
      "MATH",
      "READING",
      "SCIENCE"
    ],
    "grade": 3,
    "name": "Harriette Feest",
    "id": 248,
    "frequency": 3
  },
  {
    "courses": [
      "WRITING"
    ],
    "grade": 5,
    "name": "Trang Ratke",
    "id": 249,
    "frequency": 4
  },
  {
    "courses": [
      "WRITING",
      "HISTORY"
    ],
    "grade": 11,
    "name": "Shon Konopelski",
    "id": 250,
    "frequency": 2
  },
  {
    "courses": [
      "MATH",
      "READING",
      "SCIENCE",
      "HISTORY"
    ],
    "grade": 7,
    "name": "Avis Walsh",
    "id": 251,
    "frequency": 5
  },
  {
    "courses": [],
    "grade": 2,
    "name": "Carlos Hahn",
    "id": 252,
    "frequency": 6
  },
  {
    "courses": [
      "MATH",
      "READING",
      "WRITING"
    ],
    "grade": 8,
    "name": "Gwen Hamill",
    "id": 253,
    "frequency": 4
  },
  {
    "courses": [
      "READING",
      "WRITING",
      "HISTORY"
    ],
    "grade": 3,
    "name": "Melody Wilderman",
    "id": 254,
    "frequency": 3
  },
  {
    "courses": [
      "MATH",
      "WRITING",
      "SCIENCE",
      "HISTORY"
    ],
    "grade": 2,
    "name": "Jaime Jacobi",
    "id": 255,
    "frequency": 6
  },
  {
    "courses": [
      "MATH",
      "SCIENCE",
      "HISTORY"
    ],
    "grade": 9,
    "name": "Brent Johnson",
    "id": 256,
    "frequency": 1
  },
  {
    "courses": [
      "WRITING",
      "SCIENCE"
    ],
    "grade": 8,
    "name": "Farah Bashirian",
    "id": 257,
    "frequency": 5
  },
  {
    "courses": [
      "READING",
      "HISTORY"
    ],
    "grade": 5,
    "name": "Damien Larson",
    "id": 258,
    "frequency": 4
  },
  {
    "courses": [
      "READING",
      "WRITING"
    ],
    "grade": 10,
    "name": "Gayla Wilkinson",
    "id": 259,
    "frequency": 3
  },
  {
    "courses": [
      "MATH",
      "WRITING",
      "SCIENCE",
      "HISTORY"
    ],
    "grade": 8,
    "name": "Gordon Blanda",
    "id": 260,
    "frequency": 1
  },
  {
    "courses": [
      "READING",
      "WRITING",
      "SCIENCE"
    ],
    "grade": 9,
    "name": "Gino Senger",
    "id": 261,
    "frequency": 4
  },
  {
    "courses": [
      "MATH",
      "READING"
    ],
    "grade": 10,
    "name": "Sherman Wilkinson",
    "id": 262,
    "frequency": 1
  },
  {
    "courses": [
      "MATH",
      "READING",
      "WRITING",
      "SCIENCE"
    ],
    "grade": 8,
    "name": "Toshiko Dach",
    "id": 263,
    "frequency": 4
  },
  {
    "courses": [
      "HISTORY"
    ],
    "grade": 2,
    "name": "Molly Zulauf",
    "id": 264,
    "frequency": 4
  },
  {
    "courses": [
      "READING",
      "HISTORY"
    ],
    "grade": 7,
    "name": "Myles Hamill",
    "id": 265,
    "frequency": 2
  },
  {
    "courses": [
      "MATH",
      "READING",
      "WRITING",
      "HISTORY"
    ],
    "grade": 3,
    "name": "Joseph Ziemann",
    "id": 266,
    "frequency": 3
  },
  {
    "courses": [
      "MATH",
      "WRITING"
    ],
    "grade": 7,
    "name": "Mora Dare",
    "id": 267,
    "frequency": 4
  },
  {
    "courses": [
      "SCIENCE",
      "HISTORY"
    ],
    "grade": 9,
    "name": "Mitchel Gislason",
    "id": 268,
    "frequency": 5
  },
  {
    "courses": [
      "MATH",
      "SCIENCE",
      "HISTORY"
    ],
    "grade": 3,
    "name": "Galen Wunsch",
    "id": 269,
    "frequency": 3
  },
  {
    "courses": [
      "MATH",
      "READING",
      "WRITING"
    ],
    "grade": 7,
    "name": "Floria Bernier",
    "id": 270,
    "frequency": 3
  },
  {
    "courses": [
      "MATH",
      "SCIENCE",
      "HISTORY"
    ],
    "grade": 11,
    "name": "Deadra Bahringer",
    "id": 271,
    "frequency": 1
  },
  {
    "courses": [
      "MATH",
      "READING",
      "WRITING"
    ],
    "grade": 3,
    "name": "Lisha Wolff",
    "id": 272,
    "frequency": 5
  },
  {
    "courses": [
      "MATH",
      "SCIENCE"
    ],
    "grade": 11,
    "name": "Shayne Welch",
    "id": 273,
    "frequency": 2
  },
  {
    "courses": [
      "MATH",
      "SCIENCE"
    ],
    "grade": 7,
    "name": "Anthony Harber",
    "id": 274,
    "frequency": 1
  },
  {
    "courses": [
      "HISTORY"
    ],
    "grade": 5,
    "name": "Merle Macejkovic",
    "id": 275,
    "frequency": 5
  },
  {
    "courses": [
      "MATH",
      "READING",
      "WRITING"
    ],
    "grade": 2,
    "name": "Rey Streich",
    "id": 276,
    "frequency": 5
  },
  {
    "courses": [
      "MATH",
      "READING",
      "WRITING"
    ],
    "grade": 5,
    "name": "Michiko Sawayn",
    "id": 277,
    "frequency": 4
  },
  {
    "courses": [
      "WRITING"
    ],
    "grade": 3,
    "name": "Abigail Larkin",
    "id": 278,
    "frequency": 5
  },
  {
    "courses": [
      "SCIENCE",
      "HISTORY"
    ],
    "grade": 2,
    "name": "Kristie Kling",
    "id": 279,
    "frequency": 2
  },
  {
    "courses": [
      "MATH",
      "READING",
      "SCIENCE",
      "HISTORY"
    ],
    "grade": 9,
    "name": "Myrle Mraz",
    "id": 280,
    "frequency": 3
  },
  {
    "courses": [
      "READING"
    ],
    "grade": 2,
    "name": "Kayce Pacocha",
    "id": 281,
    "frequency": 2
  },
  {
    "courses": [
      "MATH"
    ],
    "grade": 11,
    "name": "Marcela Price",
    "id": 282,
    "frequency": 4
  },
  {
    "courses": [
      "READING"
    ],
    "grade": 6,
    "name": "Racheal Schultz",
    "id": 283,
    "frequency": 2
  },
  {
    "courses": [
      "HISTORY"
    ],
    "grade": 10,
    "name": "Ebony Abshire",
    "id": 284,
    "frequency": 3
  },
  {
    "courses": [
      "MATH",
      "HISTORY"
    ],
    "grade": 4,
    "name": "Geoffrey West",
    "id": 285,
    "frequency": 6
  },
  {
    "courses": [
      "READING",
      "WRITING",
      "HISTORY"
    ],
    "grade": 10,
    "name": "Nanci Collins",
    "id": 286,
    "frequency": 2
  },
  {
    "courses": [
      "MATH",
      "READING",
      "SCIENCE"
    ],
    "grade": 6,
    "name": "Erich O\u0027Connell",
    "id": 287,
    "frequency": 4
  },
  {
    "courses": [
      "MATH",
      "READING"
    ],
    "grade": 3,
    "name": "Trinidad Jones",
    "id": 288,
    "frequency": 2
  },
  {
    "courses": [
      "MATH",
      "SCIENCE",
      "HISTORY"
    ],
    "grade": 4,
    "name": "Lucas Spencer",
    "id": 289,
    "frequency": 2
  },
  {
    "courses": [
      "READING",
      "SCIENCE",
      "HISTORY"
    ],
    "grade": 11,
    "name": "Rosario Kreiger",
    "id": 290,
    "frequency": 5
  },
  {
    "courses": [
      "MATH",
      "SCIENCE"
    ],
    "grade": 4,
    "name": "Nakita Kuhn",
    "id": 291,
    "frequency": 6
  },
  {
    "courses": [
      "READING",
      "SCIENCE",
      "HISTORY"
    ],
    "grade": 2,
    "name": "Abe Doyle",
    "id": 292,
    "frequency": 4
  },
  {
    "courses": [
      "MATH",
      "WRITING",
      "SCIENCE"
    ],
    "grade": 10,
    "name": "Gilma Kuhlman",
    "id": 293,
    "frequency": 3
  },
  {
    "courses": [
      "READING"
    ],
    "grade": 3,
    "name": "Johanna Crona",
    "id": 294,
    "frequency": 4
  },
  {
    "courses": [
      "READING",
      "SCIENCE"
    ],
    "grade": 1,
    "name": "Elizabet Williamson",
    "id": 295,
    "frequency": 4
  },
  {
    "courses": [
      "MATH",
      "READING",
      "SCIENCE"
    ],
    "grade": 5,
    "name": "Nereida Daniel",
    "id": 296,
    "frequency": 6
  },
  {
    "courses": [
      "MATH",
      "READING"
    ],
    "grade": 3,
    "name": "Miquel Jenkins",
    "id": 297,
    "frequency": 6
  },
  {
    "courses": [
      "MATH",
      "WRITING"
    ],
    "grade": 3,
    "name": "Narcisa Grant",
    "id": 298,
    "frequency": 3
  },
  {
    "courses": [
      "SCIENCE",
      "HISTORY"
    ],
    "grade": 9,
    "name": "Tai Ebert",
    "id": 299,
    "frequency": 3
  },
  {
    "courses": [
      "READING",
      "WRITING",
      "SCIENCE",
      "HISTORY"
    ],
    "grade": 3,
    "name": "Garfield Collins",
    "id": 300,
    "frequency": 2
  },
  {
    "courses": [
      "READING"
    ],
    "grade": 9,
    "name": "Erick Murphy",
    "id": 301,
    "frequency": 5
  },
  {
    "courses": [
      "READING",
      "WRITING",
      "SCIENCE"
    ],
    "grade": 8,
    "name": "Loura Zieme",
    "id": 302,
    "frequency": 5
  },
  {
    "courses": [
      "READING",
      "WRITING",
      "SCIENCE",
      "HISTORY"
    ],
    "grade": 3,
    "name": "Denis Jast",
    "id": 303,
    "frequency": 5
  },
  {
    "courses": [
      "MATH",
      "HISTORY"
    ],
    "grade": 5,
    "name": "Elizabet Leuschke",
    "id": 304,
    "frequency": 1
  },
  {
    "courses": [
      "SCIENCE"
    ],
    "grade": 3,
    "name": "Burma Rolfson",
    "id": 305,
    "frequency": 3
  },
  {
    "courses": [
      "MATH",
      "READING",
      "WRITING"
    ],
    "grade": 2,
    "name": "Lynell Champlin",
    "id": 306,
    "frequency": 2
  },
  {
    "courses": [
      "WRITING"
    ],
    "grade": 10,
    "name": "Joni Stroman",
    "id": 307,
    "frequency": 1
  },
  {
    "courses": [
      "MATH",
      "READING",
      "HISTORY"
    ],
    "grade": 10,
    "name": "Curtis Harris",
    "id": 308,
    "frequency": 3
  },
  {
    "courses": [
      "READING",
      "WRITING",
      "SCIENCE"
    ],
    "grade": 9,
    "name": "Casey Effertz",
    "id": 309,
    "frequency": 2
  },
  {
    "courses": [
      "READING"
    ],
    "grade": 5,
    "name": "Cornelius Rath",
    "id": 310,
    "frequency": 4
  },
  {
    "courses": [
      "MATH",
      "READING",
      "WRITING",
      "SCIENCE"
    ],
    "grade": 3,
    "name": "Muoi Turcotte",
    "id": 311,
    "frequency": 4
  },
  {
    "courses": [
      "MATH",
      "WRITING"
    ],
    "grade": 2,
    "name": "Glinda Greenfelder",
    "id": 312,
    "frequency": 4
  },
  {
    "courses": [
      "MATH",
      "WRITING",
      "SCIENCE",
      "HISTORY"
    ],
    "grade": 10,
    "name": "Melvin West",
    "id": 313,
    "frequency": 3
  },
  {
    "courses": [
      "HISTORY"
    ],
    "grade": 2,
    "name": "Dee Lueilwitz",
    "id": 314,
    "frequency": 3
  },
  {
    "courses": [
      "MATH"
    ],
    "grade": 2,
    "name": "Gerry Hintz",
    "id": 315,
    "frequency": 5
  },
  {
    "courses": [
      "READING",
      "WRITING"
    ],
    "grade": 8,
    "name": "Loren D\u0027Amore",
    "id": 316,
    "frequency": 3
  },
  {
    "courses": [
      "READING",
      "WRITING",
      "SCIENCE"
    ],
    "grade": 10,
    "name": "Deann Kertzmann",
    "id": 317,
    "frequency": 5
  },
  {
    "courses": [
      "MATH",
      "READING",
      "SCIENCE"
    ],
    "grade": 9,
    "name": "Bianca Casper",
    "id": 318,
    "frequency": 5
  },
  {
    "courses": [
      "MATH",
      "HISTORY"
    ],
    "grade": 10,
    "name": "Sueann Pouros",
    "id": 319,
    "frequency": 3
  },
  {
    "courses": [
      "WRITING",
      "SCIENCE",
      "HISTORY"
    ],
    "grade": 11,
    "name": "Wenona Miller",
    "id": 320,
    "frequency": 2
  },
  {
    "courses": [
      "WRITING"
    ],
    "grade": 6,
    "name": "Hiram Powlowski",
    "id": 321,
    "frequency": 2
  },
  {
    "courses": [
      "READING"
    ],
    "grade": 9,
    "name": "Beau Barton",
    "id": 322,
    "frequency": 3
  },
  {
    "courses": [
      "MATH",
      "WRITING",
      "SCIENCE",
      "HISTORY"
    ],
    "grade": 6,
    "name": "Celina Marvin",
    "id": 323,
    "frequency": 3
  },
  {
    "courses": [
      "MATH",
      "READING",
      "HISTORY"
    ],
    "grade": 7,
    "name": "Sammy Ebert",
    "id": 324,
    "frequency": 5
  },
  {
    "courses": [
      "READING",
      "WRITING"
    ],
    "grade": 2,
    "name": "Valda Howell",
    "id": 325,
    "frequency": 3
  },
  {
    "courses": [
      "MATH",
      "READING",
      "WRITING"
    ],
    "grade": 1,
    "name": "Lory Huel",
    "id": 326,
    "frequency": 4
  },
  {
    "courses": [
      "READING",
      "WRITING",
      "SCIENCE"
    ],
    "grade": 9,
    "name": "Melba Murazik",
    "id": 327,
    "frequency": 3
  },
  {
    "courses": [
      "MATH",
      "WRITING",
      "SCIENCE",
      "HISTORY"
    ],
    "grade": 5,
    "name": "Lavern Flatley",
    "id": 328,
    "frequency": 2
  },
  {
    "courses": [
      "READING",
      "SCIENCE",
      "HISTORY"
    ],
    "grade": 3,
    "name": "Fidel Casper",
    "id": 329,
    "frequency": 6
  },
  {
    "courses": [
      "MATH",
      "READING",
      "HISTORY"
    ],
    "grade": 4,
    "name": "Adam Toy",
    "id": 330,
    "frequency": 6
  },
  {
    "courses": [
      "READING",
      "WRITING"
    ],
    "grade": 3,
    "name": "Jae Ebert",
    "id": 331,
    "frequency": 6
  },
  {
    "courses": [
      "WRITING",
      "HISTORY"
    ],
    "grade": 8,
    "name": "Gustavo Davis",
    "id": 332,
    "frequency": 3
  },
  {
    "courses": [
      "READING",
      "WRITING",
      "SCIENCE"
    ],
    "grade": 4,
    "name": "Everette Bauch",
    "id": 333,
    "frequency": 3
  },
  {
    "courses": [
      "WRITING",
      "SCIENCE",
      "HISTORY"
    ],
    "grade": 3,
    "name": "Elbert Windler",
    "id": 334,
    "frequency": 4
  },
  {
    "courses": [
      "SCIENCE"
    ],
    "grade": 5,
    "name": "Han Feest",
    "id": 335,
    "frequency": 2
  },
  {
    "courses": [
      "MATH",
      "READING",
      "WRITING"
    ],
    "grade": 9,
    "name": "Angelia Hilpert",
    "id": 336,
    "frequency": 2
  },
  {
    "courses": [
      "MATH",
      "READING",
      "SCIENCE",
      "HISTORY"
    ],
    "grade": 2,
    "name": "Romeo Rodriguez",
    "id": 337,
    "frequency": 4
  },
  {
    "courses": [
      "READING",
      "SCIENCE"
    ],
    "grade": 5,
    "name": "Eldridge Kris",
    "id": 338,
    "frequency": 4
  },
  {
    "courses": [
      "WRITING",
      "HISTORY"
    ],
    "grade": 9,
    "name": "Ned Koss",
    "id": 339,
    "frequency": 2
  },
  {
    "courses": [
      "MATH",
      "READING",
      "SCIENCE",
      "HISTORY"
    ],
    "grade": 11,
    "name": "Ellsworth Rohan",
    "id": 340,
    "frequency": 2
  },
  {
    "courses": [
      "MATH",
      "READING",
      "SCIENCE"
    ],
    "grade": 11,
    "name": "Brandon Hane",
    "id": 341,
    "frequency": 3
  },
  {
    "courses": [
      "WRITING",
      "HISTORY"
    ],
    "grade": 2,
    "name": "Kristan Smitham",
    "id": 342,
    "frequency": 4
  },
  {
    "courses": [
      "WRITING"
    ],
    "grade": 5,
    "name": "Melvin Thompson",
    "id": 343,
    "frequency": 6
  },
  {
    "courses": [
      "MATH",
      "READING",
      "SCIENCE"
    ],
    "grade": 7,
    "name": "Brian Douglas",
    "id": 344,
    "frequency": 6
  },
  {
    "courses": [
      "MATH",
      "WRITING",
      "SCIENCE"
    ],
    "grade": 11,
    "name": "Franklin Stark",
    "id": 345,
    "frequency": 1
  },
  {
    "courses": [
      "WRITING",
      "SCIENCE",
      "HISTORY"
    ],
    "grade": 3,
    "name": "Guillermo Ziemann",
    "id": 346,
    "frequency": 6
  },
  {
    "courses": [
      "MATH",
      "READING",
      "WRITING",
      "SCIENCE"
    ],
    "grade": 6,
    "name": "Bryan Stanton",
    "id": 347,
    "frequency": 6
  },
  {
    "courses": [
      "WRITING"
    ],
    "grade": 7,
    "name": "Tracie Mraz",
    "id": 348,
    "frequency": 4
  },
  {
    "courses": [],
    "grade": 2,
    "name": "Arcelia Thiel",
    "id": 349,
    "frequency": 1
  },
  {
    "courses": [
      "READING",
      "WRITING",
      "SCIENCE"
    ],
    "grade": 11,
    "name": "Joycelyn Funk",
    "id": 350,
    "frequency": 6
  },
  {
    "courses": [
      "MATH",
      "READING",
      "WRITING",
      "HISTORY"
    ],
    "grade": 7,
    "name": "Barrett Simonis",
    "id": 351,
    "frequency": 6
  },
  {
    "courses": [
      "WRITING",
      "SCIENCE"
    ],
    "grade": 4,
    "name": "Wilfred Schmidt",
    "id": 352,
    "frequency": 6
  },
  {
    "courses": [
      "MATH",
      "READING"
    ],
    "grade": 8,
    "name": "Erik Hauck",
    "id": 353,
    "frequency": 5
  },
  {
    "courses": [
      "MATH",
      "HISTORY"
    ],
    "grade": 3,
    "name": "Federico Adams",
    "id": 354,
    "frequency": 6
  },
  {
    "courses": [
      "MATH",
      "READING",
      "WRITING",
      "SCIENCE",
      "HISTORY"
    ],
    "grade": 4,
    "name": "Francis Hartmann",
    "id": 355,
    "frequency": 6
  },
  {
    "courses": [
      "MATH",
      "WRITING",
      "HISTORY"
    ],
    "grade": 11,
    "name": "Dick Erdman",
    "id": 356,
    "frequency": 3
  },
  {
    "courses": [
      "MATH",
      "READING",
      "WRITING",
      "SCIENCE"
    ],
    "grade": 10,
    "name": "Leeanna Keeling",
    "id": 357,
    "frequency": 6
  },
  {
    "courses": [
      "MATH",
      "SCIENCE",
      "HISTORY"
    ],
    "grade": 2,
    "name": "Anderson Tromp",
    "id": 358,
    "frequency": 5
  },
  {
    "courses": [
      "READING",
      "WRITING",
      "HISTORY"
    ],
    "grade": 2,
    "name": "Lavern Runolfsdottir",
    "id": 359,
    "frequency": 6
  },
  {
    "courses": [
      "MATH",
      "READING"
    ],
    "grade": 4,
    "name": "Verda Howell",
    "id": 360,
    "frequency": 4
  },
  {
    "courses": [
      "READING",
      "WRITING",
      "HISTORY"
    ],
    "grade": 5,
    "name": "Lily Klein",
    "id": 361,
    "frequency": 1
  },
  {
    "courses": [
      "MATH",
      "SCIENCE",
      "HISTORY"
    ],
    "grade": 8,
    "name": "Season Cole",
    "id": 362,
    "frequency": 5
  },
  {
    "courses": [
      "MATH",
      "WRITING"
    ],
    "grade": 2,
    "name": "Donald Kunde",
    "id": 363,
    "frequency": 2
  },
  {
    "courses": [
      "MATH",
      "WRITING",
      "SCIENCE"
    ],
    "grade": 6,
    "name": "Cecelia Schuster",
    "id": 364,
    "frequency": 4
  },
  {
    "courses": [
      "SCIENCE",
      "HISTORY"
    ],
    "grade": 10,
    "name": "Gudrun Koepp",
    "id": 365,
    "frequency": 3
  },
  {
    "courses": [
      "MATH",
      "SCIENCE",
      "HISTORY"
    ],
    "grade": 8,
    "name": "Giovanni Rowe",
    "id": 366,
    "frequency": 3
  },
  {
    "courses": [
      "MATH",
      "WRITING",
      "HISTORY"
    ],
    "grade": 10,
    "name": "Brittani VonRueden",
    "id": 367,
    "frequency": 3
  },
  {
    "courses": [
      "WRITING",
      "SCIENCE",
      "HISTORY"
    ],
    "grade": 5,
    "name": "Rufus Reilly",
    "id": 368,
    "frequency": 3
  },
  {
    "courses": [
      "MATH",
      "READING",
      "HISTORY"
    ],
    "grade": 2,
    "name": "Lavelle Nienow",
    "id": 369,
    "frequency": 4
  },
  {
    "courses": [
      "MATH",
      "WRITING"
    ],
    "grade": 7,
    "name": "Dwayne Kuhlman",
    "id": 370,
    "frequency": 5
  },
  {
    "courses": [],
    "grade": 5,
    "name": "Debbi Roob",
    "id": 371,
    "frequency": 2
  },
  {
    "courses": [
      "MATH",
      "WRITING"
    ],
    "grade": 4,
    "name": "Beaulah Lubowitz",
    "id": 372,
    "frequency": 5
  },
  {
    "courses": [
      "MATH"
    ],
    "grade": 4,
    "name": "Delaine Jerde",
    "id": 373,
    "frequency": 4
  },
  {
    "courses": [
      "READING",
      "WRITING",
      "HISTORY"
    ],
    "grade": 3,
    "name": "Lelah Torphy",
    "id": 374,
    "frequency": 4
  },
  {
    "courses": [
      "MATH",
      "WRITING",
      "SCIENCE",
      "HISTORY"
    ],
    "grade": 10,
    "name": "Jules Rutherford",
    "id": 375,
    "frequency": 3
  },
  {
    "courses": [
      "READING",
      "WRITING"
    ],
    "grade": 10,
    "name": "Brenton Lebsack",
    "id": 376,
    "frequency": 6
  },
  {
    "courses": [
      "SCIENCE"
    ],
    "grade": 11,
    "name": "Kim Kunze",
    "id": 377,
    "frequency": 3
  },
  {
    "courses": [
      "MATH",
      "READING",
      "HISTORY"
    ],
    "grade": 10,
    "name": "Santos Kozey",
    "id": 378,
    "frequency": 1
  },
  {
    "courses": [
      "MATH",
      "READING",
      "WRITING"
    ],
    "grade": 11,
    "name": "Henry Ferry",
    "id": 379,
    "frequency": 3
  },
  {
    "courses": [
      "MATH",
      "WRITING",
      "SCIENCE",
      "HISTORY"
    ],
    "grade": 3,
    "name": "Harry Lemke",
    "id": 380,
    "frequency": 3
  },
  {
    "courses": [
      "READING",
      "SCIENCE",
      "HISTORY"
    ],
    "grade": 3,
    "name": "Kim Rempel",
    "id": 381,
    "frequency": 4
  },
  {
    "courses": [
      "MATH",
      "READING",
      "WRITING",
      "SCIENCE"
    ],
    "grade": 7,
    "name": "Devon Hartmann",
    "id": 382,
    "frequency": 5
  },
  {
    "courses": [
      "HISTORY"
    ],
    "grade": 10,
    "name": "Rosalie Jacobi",
    "id": 383,
    "frequency": 3
  },
  {
    "courses": [
      "MATH",
      "WRITING",
      "SCIENCE",
      "HISTORY"
    ],
    "grade": 6,
    "name": "Naida Huel",
    "id": 384,
    "frequency": 5
  },
  {
    "courses": [
      "READING",
      "WRITING",
      "SCIENCE",
      "HISTORY"
    ],
    "grade": 8,
    "name": "Kari Hamill",
    "id": 385,
    "frequency": 6
  },
  {
    "courses": [
      "MATH"
    ],
    "grade": 11,
    "name": "Beverly Abshire",
    "id": 386,
    "frequency": 6
  },
  {
    "courses": [
      "WRITING",
      "SCIENCE",
      "HISTORY"
    ],
    "grade": 5,
    "name": "Hollis Turcotte",
    "id": 387,
    "frequency": 2
  },
  {
    "courses": [
      "MATH",
      "READING",
      "WRITING",
      "SCIENCE"
    ],
    "grade": 11,
    "name": "Maranda Conroy",
    "id": 388,
    "frequency": 3
  },
  {
    "courses": [
      "MATH",
      "READING",
      "HISTORY"
    ],
    "grade": 7,
    "name": "Carman Jaskolski",
    "id": 389,
    "frequency": 6
  },
  {
    "courses": [
      "MATH",
      "SCIENCE"
    ],
    "grade": 3,
    "name": "Marshall Bernier",
    "id": 390,
    "frequency": 1
  },
  {
    "courses": [
      "MATH",
      "READING",
      "HISTORY"
    ],
    "grade": 10,
    "name": "Alyse Ondricka",
    "id": 391,
    "frequency": 2
  },
  {
    "courses": [
      "MATH",
      "READING",
      "WRITING",
      "SCIENCE"
    ],
    "grade": 6,
    "name": "Chong Christiansen",
    "id": 392,
    "frequency": 4
  },
  {
    "courses": [
      "WRITING",
      "SCIENCE",
      "HISTORY"
    ],
    "grade": 11,
    "name": "Ericka Kassulke",
    "id": 393,
    "frequency": 5
  },
  {
    "courses": [
      "READING",
      "WRITING"
    ],
    "grade": 1,
    "name": "Adina Kautzer",
    "id": 394,
    "frequency": 2
  },
  {
    "courses": [
      "READING",
      "HISTORY"
    ],
    "grade": 11,
    "name": "Tony Koelpin",
    "id": 395,
    "frequency": 2
  },
  {
    "courses": [
      "MATH",
      "READING",
      "WRITING",
      "SCIENCE",
      "HISTORY"
    ],
    "grade": 5,
    "name": "Lane Klein",
    "id": 396,
    "frequency": 3
  },
  {
    "courses": [
      "SCIENCE",
      "HISTORY"
    ],
    "grade": 4,
    "name": "Tori Jaskolski",
    "id": 397,
    "frequency": 5
  },
  {
    "courses": [
      "READING",
      "HISTORY"
    ],
    "grade": 6,
    "name": "Bertram Emmerich",
    "id": 398,
    "frequency": 5
  },
  {
    "courses": [
      "MATH",
      "WRITING",
      "HISTORY"
    ],
    "grade": 11,
    "name": "Gaylord Collins",
    "id": 399,
    "frequency": 6
  },
  {
    "courses": [
      "WRITING",
      "SCIENCE",
      "HISTORY"
    ],
    "grade": 8,
    "name": "Anja Wyman",
    "id": 400,
    "frequency": 4
  },
  {
    "courses": [
      "MATH",
      "READING",
      "WRITING",
      "HISTORY"
    ],
    "grade": 8,
    "name": "Carrol Hayes",
    "id": 401,
    "frequency": 4
  },
  {
    "courses": [
      "WRITING",
      "SCIENCE",
      "HISTORY"
    ],
    "grade": 2,
    "name": "Sang Kuhlman",
    "id": 402,
    "frequency": 1
  },
  {
    "courses": [
      "MATH",
      "READING",
      "WRITING",
      "SCIENCE"
    ],
    "grade": 4,
    "name": "Elvis Kling",
    "id": 403,
    "frequency": 5
  },
  {
    "courses": [
      "READING",
      "SCIENCE",
      "HISTORY"
    ],
    "grade": 5,
    "name": "Brooks Nicolas",
    "id": 404,
    "frequency": 3
  },
  {
    "courses": [
      "MATH",
      "HISTORY"
    ],
    "grade": 7,
    "name": "Darius White",
    "id": 405,
    "frequency": 6
  },
  {
    "courses": [
      "MATH",
      "READING",
      "WRITING"
    ],
    "grade": 9,
    "name": "Elayne Wyman",
    "id": 406,
    "frequency": 4
  },
  {
    "courses": [
      "WRITING",
      "SCIENCE"
    ],
    "grade": 4,
    "name": "Mohammad Becker",
    "id": 407,
    "frequency": 3
  },
  {
    "courses": [
      "WRITING",
      "SCIENCE"
    ],
    "grade": 4,
    "name": "Rory Kerluke",
    "id": 408,
    "frequency": 5
  },
  {
    "courses": [
      "READING",
      "WRITING"
    ],
    "grade": 7,
    "name": "Aron Barrows",
    "id": 409,
    "frequency": 3
  },
  {
    "courses": [
      "MATH",
      "READING",
      "WRITING",
      "SCIENCE"
    ],
    "grade": 1,
    "name": "Assunta Cartwright",
    "id": 410,
    "frequency": 3
  },
  {
    "courses": [
      "MATH",
      "READING",
      "SCIENCE",
      "HISTORY"
    ],
    "grade": 9,
    "name": "Chung Beatty",
    "id": 411,
    "frequency": 5
  },
  {
    "courses": [
      "MATH",
      "WRITING",
      "SCIENCE"
    ],
    "grade": 10,
    "name": "Rolf Kassulke",
    "id": 412,
    "frequency": 2
  },
  {
    "courses": [
      "MATH"
    ],
    "grade": 8,
    "name": "Fredrick Schultz",
    "id": 413,
    "frequency": 2
  },
  {
    "courses": [
      "MATH",
      "SCIENCE"
    ],
    "grade": 9,
    "name": "Teodoro Hand",
    "id": 414,
    "frequency": 6
  },
  {
    "courses": [
      "MATH",
      "WRITING",
      "SCIENCE",
      "HISTORY"
    ],
    "grade": 2,
    "name": "Ken Feest",
    "id": 415,
    "frequency": 4
  },
  {
    "courses": [
      "WRITING",
      "SCIENCE",
      "HISTORY"
    ],
    "grade": 10,
    "name": "Sanjuanita Erdman",
    "id": 416,
    "frequency": 6
  },
  {
    "courses": [
      "MATH",
      "READING",
      "WRITING"
    ],
    "grade": 3,
    "name": "Solomon Greenfelder",
    "id": 417,
    "frequency": 4
  },
  {
    "courses": [
      "READING",
      "WRITING",
      "HISTORY"
    ],
    "grade": 7,
    "name": "Inger Upton",
    "id": 418,
    "frequency": 2
  },
  {
    "courses": [
      "MATH",
      "WRITING",
      "SCIENCE"
    ],
    "grade": 6,
    "name": "Robert Upton",
    "id": 419,
    "frequency": 5
  },
  {
    "courses": [
      "MATH",
      "WRITING",
      "SCIENCE",
      "HISTORY"
    ],
    "grade": 5,
    "name": "Eugenia Vandervort",
    "id": 420,
    "frequency": 3
  },
  {
    "courses": [
      "READING",
      "HISTORY"
    ],
    "grade": 3,
    "name": "Marylouise Bradtke",
    "id": 421,
    "frequency": 1
  },
  {
    "courses": [
      "MATH",
      "READING",
      "HISTORY"
    ],
    "grade": 3,
    "name": "Valentin Renner",
    "id": 422,
    "frequency": 4
  },
  {
    "courses": [
      "READING",
      "SCIENCE"
    ],
    "grade": 11,
    "name": "Hector Bins",
    "id": 423,
    "frequency": 6
  },
  {
    "courses": [
      "MATH",
      "READING",
      "WRITING",
      "SCIENCE"
    ],
    "grade": 3,
    "name": "Gertrude Collins",
    "id": 424,
    "frequency": 3
  },
  {
    "courses": [
      "READING",
      "WRITING"
    ],
    "grade": 7,
    "name": "Wesley Pfeffer",
    "id": 425,
    "frequency": 4
  },
  {
    "courses": [
      "READING",
      "WRITING"
    ],
    "grade": 10,
    "name": "Lorna Muller",
    "id": 426,
    "frequency": 1
  },
  {
    "courses": [
      "MATH",
      "WRITING",
      "SCIENCE",
      "HISTORY"
    ],
    "grade": 2,
    "name": "Otto Welch",
    "id": 427,
    "frequency": 6
  },
  {
    "courses": [
      "WRITING",
      "HISTORY"
    ],
    "grade": 4,
    "name": "Quinn Considine",
    "id": 428,
    "frequency": 2
  },
  {
    "courses": [
      "MATH",
      "SCIENCE",
      "HISTORY"
    ],
    "grade": 10,
    "name": "Michael Kiehn",
    "id": 429,
    "frequency": 5
  },
  {
    "courses": [
      "READING",
      "SCIENCE",
      "HISTORY"
    ],
    "grade": 1,
    "name": "Janell Mante",
    "id": 430,
    "frequency": 4
  },
  {
    "courses": [
      "MATH",
      "WRITING",
      "SCIENCE",
      "HISTORY"
    ],
    "grade": 4,
    "name": "Sparkle King",
    "id": 431,
    "frequency": 5
  },
  {
    "courses": [
      "SCIENCE",
      "HISTORY"
    ],
    "grade": 9,
    "name": "Henry Nolan",
    "id": 432,
    "frequency": 6
  },
  {
    "courses": [
      "MATH",
      "HISTORY"
    ],
    "grade": 11,
    "name": "Harold Goodwin",
    "id": 433,
    "frequency": 4
  },
  {
    "courses": [
      "READING",
      "WRITING",
      "SCIENCE"
    ],
    "grade": 11,
    "name": "Irwin Kovacek",
    "id": 434,
    "frequency": 4
  },
  {
    "courses": [
      "MATH",
      "SCIENCE"
    ],
    "grade": 7,
    "name": "Lynwood Johnston",
    "id": 435,
    "frequency": 4
  },
  {
    "courses": [
      "MATH"
    ],
    "grade": 1,
    "name": "Columbus Weimann",
    "id": 436,
    "frequency": 2
  },
  {
    "courses": [
      "WRITING",
      "SCIENCE",
      "HISTORY"
    ],
    "grade": 10,
    "name": "Ryan Predovic",
    "id": 437,
    "frequency": 4
  },
  {
    "courses": [
      "SCIENCE",
      "HISTORY"
    ],
    "grade": 6,
    "name": "Moses Sauer",
    "id": 438,
    "frequency": 6
  },
  {
    "courses": [
      "MATH",
      "READING",
      "SCIENCE"
    ],
    "grade": 3,
    "name": "Ok Smitham",
    "id": 439,
    "frequency": 5
  },
  {
    "courses": [
      "MATH",
      "READING",
      "WRITING"
    ],
    "grade": 8,
    "name": "Weston Greenfelder",
    "id": 440,
    "frequency": 1
  },
  {
    "courses": [
      "READING",
      "WRITING",
      "HISTORY"
    ],
    "grade": 8,
    "name": "Lawanna Powlowski",
    "id": 441,
    "frequency": 4
  },
  {
    "courses": [
      "MATH",
      "READING",
      "SCIENCE",
      "HISTORY"
    ],
    "grade": 9,
    "name": "Siu Green",
    "id": 442,
    "frequency": 4
  },
  {
    "courses": [
      "MATH",
      "READING",
      "WRITING",
      "SCIENCE"
    ],
    "grade": 3,
    "name": "Chet Auer",
    "id": 443,
    "frequency": 1
  },
  {
    "courses": [
      "MATH",
      "READING",
      "WRITING",
      "SCIENCE"
    ],
    "grade": 3,
    "name": "Damon Sauer",
    "id": 444,
    "frequency": 5
  },
  {
    "courses": [
      "READING",
      "SCIENCE"
    ],
    "grade": 11,
    "name": "Chang Shanahan",
    "id": 445,
    "frequency": 2
  },
  {
    "courses": [
      "MATH",
      "WRITING",
      "HISTORY"
    ],
    "grade": 5,
    "name": "Crysta Reichert",
    "id": 446,
    "frequency": 4
  },
  {
    "courses": [
      "MATH",
      "READING",
      "SCIENCE"
    ],
    "grade": 7,
    "name": "Leandro Reynolds",
    "id": 447,
    "frequency": 3
  },
  {
    "courses": [
      "MATH",
      "WRITING"
    ],
    "grade": 9,
    "name": "Lessie Buckridge",
    "id": 448,
    "frequency": 1
  },
  {
    "courses": [
      "MATH",
      "READING",
      "WRITING",
      "SCIENCE",
      "HISTORY"
    ],
    "grade": 2,
    "name": "Wei Corwin",
    "id": 449,
    "frequency": 6
  },
  {
    "courses": [
      "MATH",
      "SCIENCE"
    ],
    "grade": 1,
    "name": "Shaunta White",
    "id": 450,
    "frequency": 3
  },
  {
    "courses": [
      "READING"
    ],
    "grade": 10,
    "name": "Herb Ratke",
    "id": 451,
    "frequency": 2
  },
  {
    "courses": [
      "READING",
      "WRITING",
      "HISTORY"
    ],
    "grade": 9,
    "name": "Truman Gerhold",
    "id": 452,
    "frequency": 4
  },
  {
    "courses": [
      "MATH",
      "WRITING",
      "SCIENCE",
      "HISTORY"
    ],
    "grade": 10,
    "name": "Jacquie Schultz",
    "id": 453,
    "frequency": 5
  },
  {
    "courses": [
      "MATH",
      "WRITING",
      "SCIENCE"
    ],
    "grade": 2,
    "name": "Terry Prosacco",
    "id": 454,
    "frequency": 5
  },
  {
    "courses": [
      "MATH",
      "READING",
      "SCIENCE"
    ],
    "grade": 8,
    "name": "John Schulist",
    "id": 455,
    "frequency": 4
  },
  {
    "courses": [
      "WRITING",
      "SCIENCE"
    ],
    "grade": 8,
    "name": "Bernadine Greenholt",
    "id": 456,
    "frequency": 2
  },
  {
    "courses": [
      "MATH",
      "READING",
      "WRITING",
      "HISTORY"
    ],
    "grade": 11,
    "name": "Felicitas Stehr",
    "id": 457,
    "frequency": 5
  },
  {
    "courses": [
      "MATH",
      "WRITING",
      "HISTORY"
    ],
    "grade": 6,
    "name": "Illa Schowalter",
    "id": 458,
    "frequency": 1
  },
  {
    "courses": [
      "WRITING",
      "SCIENCE",
      "HISTORY"
    ],
    "grade": 6,
    "name": "Sharon Homenick",
    "id": 459,
    "frequency": 2
  },
  {
    "courses": [
      "WRITING",
      "HISTORY"
    ],
    "grade": 6,
    "name": "Jackson Kris",
    "id": 460,
    "frequency": 6
  },
  {
    "courses": [
      "MATH",
      "SCIENCE",
      "HISTORY"
    ],
    "grade": 9,
    "name": "Winifred Sawayn",
    "id": 461,
    "frequency": 6
  },
  {
    "courses": [
      "SCIENCE"
    ],
    "grade": 11,
    "name": "Adeline Wilderman",
    "id": 462,
    "frequency": 4
  },
  {
    "courses": [
      "MATH",
      "READING",
      "SCIENCE"
    ],
    "grade": 3,
    "name": "Gilberto Harvey",
    "id": 463,
    "frequency": 4
  },
  {
    "courses": [
      "HISTORY"
    ],
    "grade": 8,
    "name": "Mignon Roob",
    "id": 464,
    "frequency": 4
  },
  {
    "courses": [
      "MATH",
      "SCIENCE",
      "HISTORY"
    ],
    "grade": 11,
    "name": "Danny Jaskolski",
    "id": 465,
    "frequency": 3
  },
  {
    "courses": [
      "MATH",
      "READING",
      "SCIENCE",
      "HISTORY"
    ],
    "grade": 7,
    "name": "Curt Gleichner",
    "id": 466,
    "frequency": 3
  },
  {
    "courses": [
      "READING",
      "WRITING",
      "HISTORY"
    ],
    "grade": 5,
    "name": "Joel Sauer",
    "id": 467,
    "frequency": 4
  },
  {
    "courses": [
      "MATH",
      "READING",
      "WRITING"
    ],
    "grade": 2,
    "name": "Delta Senger",
    "id": 468,
    "frequency": 4
  },
  {
    "courses": [
      "MATH",
      "READING"
    ],
    "grade": 3,
    "name": "Bruce Haag",
    "id": 469,
    "frequency": 2
  },
  {
    "courses": [
      "READING",
      "SCIENCE",
      "HISTORY"
    ],
    "grade": 3,
    "name": "Tyson Reilly",
    "id": 470,
    "frequency": 1
  },
  {
    "courses": [
      "WRITING",
      "HISTORY"
    ],
    "grade": 8,
    "name": "Yong Ullrich",
    "id": 471,
    "frequency": 4
  },
  {
    "courses": [
      "MATH",
      "READING",
      "WRITING",
      "SCIENCE"
    ],
    "grade": 8,
    "name": "Sherley Kessler",
    "id": 472,
    "frequency": 3
  },
  {
    "courses": [
      "READING",
      "HISTORY"
    ],
    "grade": 4,
    "name": "Jolene Lueilwitz",
    "id": 473,
    "frequency": 4
  },
  {
    "courses": [
      "MATH",
      "READING",
      "WRITING",
      "HISTORY"
    ],
    "grade": 6,
    "name": "Ta Conroy",
    "id": 474,
    "frequency": 5
  },
  {
    "courses": [
      "MATH",
      "READING",
      "HISTORY"
    ],
    "grade": 7,
    "name": "Maurine Osinski",
    "id": 475,
    "frequency": 5
  },
  {
    "courses": [
      "SCIENCE"
    ],
    "grade": 11,
    "name": "Tory Turner",
    "id": 476,
    "frequency": 5
  },
  {
    "courses": [
      "SCIENCE",
      "HISTORY"
    ],
    "grade": 2,
    "name": "Michale Gorczany",
    "id": 477,
    "frequency": 6
  },
  {
    "courses": [
      "MATH",
      "WRITING",
      "SCIENCE"
    ],
    "grade": 4,
    "name": "Brock Funk",
    "id": 478,
    "frequency": 1
  },
  {
    "courses": [
      "MATH",
      "HISTORY"
    ],
    "grade": 3,
    "name": "Jeramy Greenholt",
    "id": 479,
    "frequency": 5
  },
  {
    "courses": [
      "HISTORY"
    ],
    "grade": 6,
    "name": "Felicia Schoen",
    "id": 480,
    "frequency": 1
  },
  {
    "courses": [
      "MATH",
      "READING"
    ],
    "grade": 4,
    "name": "Chante Satterfield",
    "id": 481,
    "frequency": 2
  },
  {
    "courses": [
      "READING"
    ],
    "grade": 4,
    "name": "Edmond Kovacek",
    "id": 482,
    "frequency": 4
  },
  {
    "courses": [
      "HISTORY"
    ],
    "grade": 8,
    "name": "Shantelle Franecki",
    "id": 483,
    "frequency": 3
  },
  {
    "courses": [
      "SCIENCE",
      "HISTORY"
    ],
    "grade": 7,
    "name": "Everett Orn",
    "id": 484,
    "frequency": 1
  },
  {
    "courses": [],
    "grade": 10,
    "name": "Guillermo Daugherty",
    "id": 485,
    "frequency": 1
  },
  {
    "courses": [
      "MATH",
      "SCIENCE"
    ],
    "grade": 1,
    "name": "Lorretta Quitzon",
    "id": 486,
    "frequency": 5
  },
  {
    "courses": [
      "MATH",
      "READING",
      "WRITING"
    ],
    "grade": 2,
    "name": "Charlott Streich",
    "id": 487,
    "frequency": 4
  },
  {
    "courses": [
      "MATH",
      "READING",
      "HISTORY"
    ],
    "grade": 1,
    "name": "Alton Gusikowski",
    "id": 488,
    "frequency": 3
  },
  {
    "courses": [
      "MATH",
      "HISTORY"
    ],
    "grade": 7,
    "name": "Belinda Cole",
    "id": 489,
    "frequency": 2
  },
  {
    "courses": [
      "READING",
      "WRITING",
      "SCIENCE"
    ],
    "grade": 8,
    "name": "Angelina Labadie",
    "id": 490,
    "frequency": 6
  },
  {
    "courses": [
      "MATH",
      "READING",
      "HISTORY"
    ],
    "grade": 3,
    "name": "Hedwig Heller",
    "id": 491,
    "frequency": 6
  },
  {
    "courses": [
      "WRITING",
      "SCIENCE"
    ],
    "grade": 5,
    "name": "Lowell Kling",
    "id": 492,
    "frequency": 6
  },
  {
    "courses": [
      "READING",
      "SCIENCE",
      "HISTORY"
    ],
    "grade": 6,
    "name": "Kati Raynor",
    "id": 493,
    "frequency": 2
  },
  {
    "courses": [
      "READING"
    ],
    "grade": 11,
    "name": "Sherman Roberts",
    "id": 494,
    "frequency": 1
  },
  {
    "courses": [
      "MATH",
      "SCIENCE"
    ],
    "grade": 9,
    "name": "Song Wolf",
    "id": 495,
    "frequency": 5
  },
  {
    "courses": [
      "READING",
      "SCIENCE"
    ],
    "grade": 2,
    "name": "Gilberte Parker",
    "id": 496,
    "frequency": 3
  },
  {
    "courses": [
      "READING",
      "WRITING",
      "SCIENCE",
      "HISTORY"
    ],
    "grade": 10,
    "name": "Lynda Beier",
    "id": 497,
    "frequency": 3
  },
  {
    "courses": [
      "MATH",
      "READING",
      "WRITING",
      "HISTORY"
    ],
    "grade": 7,
    "name": "Linda Crona",
    "id": 498,
    "frequency": 5
  },
  {
    "courses": [
      "MATH",
      "READING",
      "SCIENCE",
      "HISTORY"
    ],
    "grade": 9,
    "name": "Millie Kuphal",
    "id": 499,
    "frequency": 6
  }
]